Workbook

Sheet Instructions
A1: South Dakota Sales Tax Report — Tea, SD Hotel
A3: How to use
A4: 1. Open the 'Setup' sheet and confirm filing month, use-tax amount, and tax rates.
A5: 2. Export Cloudbeds reservation-level revenue for the CURRENT filing month and paste into 'Raw_CurrentMonth'.
A6: 3. Export reservation-level revenue for the PRIOR month and paste into 'Raw_PriorMonth' (used only for 28-day lookback).
A7: 4. For any state-government reservation, set 'StateExempt' to TRUE in the raw data row.
A8: 5. The 'Tax_Summary' sheet auto-fills. The 'State_Filing' sheet shows the exact dollar amounts to type into the state portal.
A10: Color key
A11: Yellow cells = inputs you fill in
A12: Blue text = user-entered values or rates
A13: Black text = formulas (do not overwrite)
A14: Green text = pulled from another sheet in this workbook
... A43: L: RoomRateAdjustments ($)

Sheet Setup
A1: Setup & Rates
A3: Filing Period
A4: Filing Month (text, e.g. March 2026) | B4: March 2026
A5: Year (number) | B5: 2026
A6: Use Tax Base ($) — items bought tax-free and used | B6: 0
A8: Tax Rates (SD + Tea)
A9: State sales/use tax | B9: 0.042 | C9: SD DOR — tax fact sheet 'Hotels, Motels and Campgrounds'
A10: Municipal sales tax (Tea) | B10: 0.02 | C10: City of Tea — 2% municipal sales tax
A11: Municipal Gross Receipts Tax (BBB) | B11: 0.01 | C11: SD DOR — 1% on lodging, prepared food, alcohol, admissions
A12: Tourism tax (lodging only) | B12: 0.015 | C12: SD DOR — Tourism Tax Fact Sheet, 1.5% on lodging gross receipts
A14: Cell references used in formulas:
A15: B4 | B15: Filing Month
A16: B6 | B16: Use Tax Base
A17: B9 | B17: State sales/use rate (4.2%)
A18: B10 | B18: Municipal sales rate (2.0%)
A19: B11 | B19: Municipal gross receipts rate (1.0%)
A20: B12 | B20: Tourism rate (1.5%)

Sheet Raw_CurrentMonth
A1: ReservationID | B1: GuestName | C1: CheckIn | D1: CheckOut | E1: NightsThisMonth | F1: ReservationSource | G1: StateExempt | H1: RoomRevenue | I1: PetFees | J1: OtherItemsAndServices | K1: Bartab | L1: RoomRateAdjustments | M1: PriorMonthNights | N1: TotalNights | O1: Is28DayExempt | P1: IsAnyExempt | Q1: TotalRowRevenue | R1: TaxableRowRevenue | S1: TaxableRoomRevenue | T1: TaxablePetFees | U1: TaxableOtherItems | V1: TaxableBartab | W1: TaxableRoomAdj | X1: LodgingTourismBase | Y1: StateAgencyExemptRevenue | Z1: TwentyEightDayExemptRev
M2: =IFERROR(IF(A2="","",IFERROR(VLOOKUP(A2,Raw_PriorMonth!A:E,5,FALSE),0)),0) | N2: =IF(A2="","",IFERROR(E2,0)+IFERROR(M2,0)) | O2: =IF(A2="","",IF(N2>=28,TRUE,FALSE)) | P2: =IF(A2="","",OR(G2=TRUE,O2=TRUE)) | Q2: =IF(A2="","",IFERROR(H2,0)+IFERROR(I2,0)+IFERROR(J2,0)+IFERROR(K2,0)+IFERROR(L2,0)) | R2: =IF(A2="","",IF(P2=TRUE,0,Q2)) | S2: =IF(A2="","",IF(P2=TRUE,0,IFERROR(H2,0))) | T2: =IF(A2="","",IF(P2=TRUE,0,IFERROR(I2,0))) | U2: =IF(A2="","",IF(P2=TRUE,0,IFERROR(J2,0))) | V2: =IF(A2="","",IF(P2=TRUE,0,IFERROR(K2,0))) | W2: =IF(A2="","",IF(P2=TRUE,0,IFERROR(L2,0))) | X2: =IF(A2="","",IF(P2=TRUE,0,IFERROR(H2,0)+IFERROR(I2,0)+IFERROR(L2,0))) | Y2: =IF(A2="",0,IF(G2=TRUE,IFERROR(H2,0)+IFERROR(I2,0)+IFERROR(J2,0)+IFERROR(K2,0)+IFERROR(L2,0),0)) | Z2: =IF(A2="",0,IF(AND(O2=TRUE,G2<>TRUE),IFERROR(H2,0)+IFERROR(I2,0)+IFERROR(J2,0)+IFERROR(K2,0)+IFERROR(L2,0),0))
M3: =IFERROR(IF(A3="","",IFERROR(VLOOKUP(A3,Raw_PriorMonth!A:E,5,FALSE),0)),0) | N3: =IF(A3="","",IFERROR(E3,0)+IFERROR(M3,0)) | O3: =IF(A3="","",IF(N3>=28,TRUE,FALSE)) | P3: =IF(A3="","",OR(G3=TRUE,O3=TRUE)) | Q3: =IF(A3="","",IFERROR(H3,0)+IFERROR(I3,0)+IFERROR(J3,0)+IFERROR(K3,0)+IFERROR(L3,0)) | R3: =IF(A3="","",IF(P3=TRUE,0,Q3)) | S3: =IF(A3="","",IF(P3=TRUE,0,IFERROR(H3,0))) | T3: =IF(A3="","",IF(P3=TRUE,0,IFERROR(I3,0))) | U3: =IF(A3="","",IF(P3=TRUE,0,IFERROR(J3,0))) | V3: =IF(A3="","",IF(P3=TRUE,0,IFERROR(K3,0))) | W3: =IF(A3="","",IF(P3=TRUE,0,IFERROR(L3,0))) | X3: =IF(A3="","",IF(P3=TRUE,0,IFERROR(H3,0)+IFERROR(I3,0)+IFERROR(L3,0))) | Y3: =IF(A3="",0,IF(G3=TRUE,IFERROR(H3,0)+IFERROR(I3,0)+IFERROR(J3,0)+IFERROR(K3,0)+IFERROR(L3,0),0)) | Z3: =IF(A3="",0,IF(AND(O3=TRUE,G3<>TRUE),IFERROR(H3,0)+IFERROR(I3,0)+IFERROR(J3,0)+IFERROR(K3,0)+IFERROR(L3,0),0))
M4: =IFERROR(IF(A4="","",IFERROR(VLOOKUP(A4,Raw_PriorMonth!A:E,5,FALSE),0)),0) | N4: =IF(A4="","",IFERROR(E4,0)+IFERROR(M4,0)) | O4: =IF(A4="","",IF(N4>=28,TRUE,FALSE)) | P4: =IF(A4="","",OR(G4=TRUE,O4=TRUE)) | Q4: =IF(A4="","",IFERROR(H4,0)+IFERROR(I4,0)+IFERROR(J4,0)+IFERROR(K4,0)+IFERROR(L4,0)) | R4: =IF(A4="","",IF(P4=TRUE,0,Q4)) | S4: =IF(A4="","",IF(P4=TRUE,0,IFERROR(H4,0))) | T4: =IF(A4="","",IF(P4=TRUE,0,IFERROR(I4,0))) | U4: =IF(A4="","",IF(P4=TRUE,0,IFERROR(J4,0))) | V4: =IF(A4="","",IF(P4=TRUE,0,IFERROR(K4,0))) | W4: =IF(A4="","",IF(P4=TRUE,0,IFERROR(L4,0))) | X4: =IF(A4="","",IF(P4=TRUE,0,IFERROR(H4,0)+IFERROR(I4,0)+IFERROR(L4,0))) | Y4: =IF(A4="",0,IF(G4=TRUE,IFERROR(H4,0)+IFERROR(I4,0)+IFERROR(J4,0)+IFERROR(K4,0)+IFERROR(L4,0),0)) | Z4: =IF(A4="",0,IF(AND(O4=TRUE,G4<>TRUE),IFERROR(H4,0)+IFERROR(I4,0)+IFERROR(J4,0)+IFERROR(K4,0)+IFERROR(L4,0),0))
M5: =IFERROR(IF(A5="","",IFERROR(VLOOKUP(A5,Raw_PriorMonth!A:E,5,FALSE),0)),0) | N5: =IF(A5="","",IFERROR(E5,0)+IFERROR(M5,0)) | O5: =IF(A5="","",IF(N5>=28,TRUE,FALSE)) | P5: =IF(A5="","",OR(G5=TRUE,O5=TRUE)) | Q5: =IF(A5="","",IFERROR(H5,0)+IFERROR(I5,0)+IFERROR(J5,0)+IFERROR(K5,0)+IFERROR(L5,0)) | R5: =IF(A5="","",IF(P5=TRUE,0,Q5)) | S5: =IF(A5="","",IF(P5=TRUE,0,IFERROR(H5,0))) | T5: =IF(A5="","",IF(P5=TRUE,0,IFERROR(I5,0))) | U5: =IF(A5="","",IF(P5=TRUE,0,IFERROR(J5,0))) | V5: =IF(A5="","",IF(P5=TRUE,0,IFERROR(K5,0))) | W5: =IF(A5="","",IF(P5=TRUE,0,IFERROR(L5,0))) | X5: =IF(A5="","",IF(P5=TRUE,0,IFERROR(H5,0)+IFERROR(I5,0)+IFERROR(L5,0))) | Y5: =IF(A5="",0,IF(G5=TRUE,IFERROR(H5,0)+IFERROR(I5,0)+IFERROR(J5,0)+IFERROR(K5,0)+IFERROR(L5,0),0)) | Z5: =IF(A5="",0,IF(AND(O5=TRUE,G5<>TRUE),IFERROR(H5,0)+IFERROR(I5,0)+IFERROR(J5,0)+IFERROR(K5,0)+IFERROR(L5,0),0))
M6: =IFERROR(IF(A6="","",IFERROR(VLOOKUP(A6,Raw_PriorMonth!A:E,5,FALSE),0)),0) | N6: =IF(A6="","",IFERROR(E6,0)+IFERROR(M6,0)) | O6: =IF(A6="","",IF(N6>=28,TRUE,FALSE)) | P6: =IF(A6="","",OR(G6=TRUE,O6=TRUE)) | Q6: =IF(A6="","",IFERROR(H6,0)+IFERROR(I6,0)+IFERROR(J6,0)+IFERROR(K6,0)+IFERROR(L6,0)) | R6: =IF(A6="","",IF(P6=TRUE,0,Q6)) | S6: =IF(A6="","",IF(P6=TRUE,0,IFERROR(H6,0))) | T6: =IF(A6="","",IF(P6=TRUE,0,IFERROR(I6,0))) | U6: =IF(A6="","",IF(P6=TRUE,0,IFERROR(J6,0))) | V6: =IF(A6="","",IF(P6=TRUE,0,IFERROR(K6,0))) | W6: =IF(A6="","",IF(P6=TRUE,0,IFERROR(L6,0))) | X6: =IF(A6="","",IF(P6=TRUE,0,IFERROR(H6,0)+IFERROR(I6,0)+IFERROR(L6,0))) | Y6: =IF(A6="",0,IF(G6=TRUE,IFERROR(H6,0)+IFERROR(I6,0)+IFERROR(J6,0)+IFERROR(K6,0)+IFERROR(L6,0),0)) | Z6: =IF(A6="",0,IF(AND(O6=TRUE,G6<>TRUE),IFERROR(H6,0)+IFERROR(I6,0)+IFERROR(J6,0)+IFERROR(K6,0)+IFERROR(L6,0),0))
M7: =IFERROR(IF(A7="","",IFERROR(VLOOKUP(A7,Raw_PriorMonth!A:E,5,FALSE),0)),0) | N7: =IF(A7="","",IFERROR(E7,0)+IFERROR(M7,0)) | O7: =IF(A7="","",IF(N7>=28,TRUE,FALSE)) | P7: =IF(A7="","",OR(G7=TRUE,O7=TRUE)) | Q7: =IF(A7="","",IFERROR(H7,0)+IFERROR(I7,0)+IFERROR(J7,0)+IFERROR(K7,0)+IFERROR(L7,0)) | R7: =IF(A7="","",IF(P7=TRUE,0,Q7)) | S7: =IF(A7="","",IF(P7=TRUE,0,IFERROR(H7,0))) | T7: =IF(A7="","",IF(P7=TRUE,0,IFERROR(I7,0))) | U7: =IF(A7="","",IF(P7=TRUE,0,IFERROR(J7,0))) | V7: =IF(A7="","",IF(P7=TRUE,0,IFERROR(K7,0))) | W7: =IF(A7="","",IF(P7=TRUE,0,IFERROR(L7,0))) | X7: =IF(A7="","",IF(P7=TRUE,0,IFERROR(H7,0)+IFERROR(I7,0)+IFERROR(L7,0))) | Y7: =IF(A7="",0,IF(G7=TRUE,IFERROR(H7,0)+IFERROR(I7,0)+IFERROR(J7,0)+IFERROR(K7,0)+IFERROR(L7,0),0)) | Z7: =IF(A7="",0,IF(AND(O7=TRUE,G7<>TRUE),IFERROR(H7,0)+IFERROR(I7,0)+IFERROR(J7,0)+IFERROR(K7,0)+IFERROR(L7,0),0))
M8: =IFERROR(IF(A8="","",IFERROR(VLOOKUP(A8,Raw_PriorMonth!A:E,5,FALSE),0)),0) | N8: =IF(A8="","",IFERROR(E8,0)+IFERROR(M8,0)) | O8: =IF(A8="","",IF(N8>=28,TRUE,FALSE)) | P8: =IF(A8="","",OR(G8=TRUE,O8=TRUE)) | Q8: =IF(A8="","",IFERROR(H8,0)+IFERROR(I8,0)+IFERROR(J8,0)+IFERROR(K8,0)+IFERROR(L8,0)) | R8: =IF(A8="","",IF(P8=TRUE,0,Q8)) | S8: =IF(A8="","",IF(P8=TRUE,0,IFERROR(H8,0))) | T8: =IF(A8="","",IF(P8=TRUE,0,IFERROR(I8,0))) | U8: =IF(A8="","",IF(P8=TRUE,0,IFERROR(J8,0))) | V8: =IF(A8="","",IF(P8=TRUE,0,IFERROR(K8,0))) | W8: =IF(A8="","",IF(P8=TRUE,0,IFERROR(L8,0))) | X8: =IF(A8="","",IF(P8=TRUE,0,IFERROR(H8,0)+IFERROR(I8,0)+IFERROR(L8,0))) | Y8: =IF(A8="",0,IF(G8=TRUE,IFERROR(H8,0)+IFERROR(I8,0)+IFERROR(J8,0)+IFERROR(K8,0)+IFERROR(L8,0),0)) | Z8: =IF(A8="",0,IF(AND(O8=TRUE,G8<>TRUE),IFERROR(H8,0)+IFERROR(I8,0)+IFERROR(J8,0)+IFERROR(K8,0)+IFERROR(L8,0),0))
M9: =IFERROR(IF(A9="","",IFERROR(VLOOKUP(A9,Raw_PriorMonth!A:E,5,FALSE),0)),0) | N9: =IF(A9="","",IFERROR(E9,0)+IFERROR(M9,0)) | O9: =IF(A9="","",IF(N9>=28,TRUE,FALSE)) | P9: =IF(A9="","",OR(G9=TRUE,O9=TRUE)) | Q9: =IF(A9="","",IFERROR(H9,0)+IFERROR(I9,0)+IFERROR(J9,0)+IFERROR(K9,0)+IFERROR(L9,0)) | R9: =IF(A9="","",IF(P9=TRUE,0,Q9)) | S9: =IF(A9="","",IF(P9=TRUE,0,IFERROR(H9,0))) | T9: =IF(A9="","",IF(P9=TRUE,0,IFERROR(I9,0))) | U9: =IF(A9="","",IF(P9=TRUE,0,IFERROR(J9,0))) | V9: =IF(A9="","",IF(P9=TRUE,0,IFERROR(K9,0))) | W9: =IF(A9="","",IF(P9=TRUE,0,IFERROR(L9,0))) | X9: =IF(A9="","",IF(P9=TRUE,0,IFERROR(H9,0)+IFERROR(I9,0)+IFERROR(L9,0))) | Y9: =IF(A9="",0,IF(G9=TRUE,IFERROR(H9,0)+IFERROR(I9,0)+IFERROR(J9,0)+IFERROR(K9,0)+IFERROR(L9,0),0)) | Z9: =IF(A9="",0,IF(AND(O9=TRUE,G9<>TRUE),IFERROR(H9,0)+IFERROR(I9,0)+IFERROR(J9,0)+IFERROR(K9,0)+IFERROR(L9,0),0))
M10: =IFERROR(IF(A10="","",IFERROR(VLOOKUP(A10,Raw_PriorMonth!A:E,5,FALSE),0)),0) | N10: =IF(A10="","",IFERROR(E10,0)+IFERROR(M10,0)) | O10: =IF(A10="","",IF(N10>=28,TRUE,FALSE)) | P10: =IF(A10="","",OR(G10=TRUE,O10=TRUE)) | Q10: =IF(A10="","",IFERROR(H10,0)+IFERROR(I10,0)+IFERROR(J10,0)+IFERROR(K10,0)+IFERROR(L10,0)) | R10: =IF(A10="","",IF(P10=TRUE,0,Q10)) | S10: =IF(A10="","",IF(P10=TRUE,0,IFERROR(H10,0))) | T10: =IF(A10="","",IF(P10=TRUE,0,IFERROR(I10,0))) | U10: =IF(A10="","",IF(P10=TRUE,0,IFERROR(J10,0))) | V10: =IF(A10="","",IF(P10=TRUE,0,IFERROR(K10,0))) | W10: =IF(A10="","",IF(P10=TRUE,0,IFERROR(L10,0))) | X10: =IF(A10="","",IF(P10=TRUE,0,IFERROR(H10,0)+IFERROR(I10,0)+IFERROR(L10,0))) | Y10: =IF(A10="",0,IF(G10=TRUE,IFERROR(H10,0)+IFERROR(I10,0)+IFERROR(J10,0)+IFERROR(K10,0)+IFERROR(L10,0),0)) | Z10: =IF(A10="",0,IF(AND(O10=TRUE,G10<>TRUE),IFERROR(H10,0)+IFERROR(I10,0)+IFERROR(J10,0)+IFERROR(K10,0)+IFERROR(L10,0),0))
M11: =IFERROR(IF(A11="","",IFERROR(VLOOKUP(A11,Raw_PriorMonth!A:E,5,FALSE),0)),0) | N11: =IF(A11="","",IFERROR(E11,0)+IFERROR(M11,0)) | O11: =IF(A11="","",IF(N11>=28,TRUE,FALSE)) | P11: =IF(A11="","",OR(G11=TRUE,O11=TRUE)) | Q11: =IF(A11="","",IFERROR(H11,0)+IFERROR(I11,0)+IFERROR(J11,0)+IFERROR(K11,0)+IFERROR(L11,0)) | R11: =IF(A11="","",IF(P11=TRUE,0,Q11)) | S11: =IF(A11="","",IF(P11=TRUE,0,IFERROR(H11,0))) | T11: =IF(A11="","",IF(P11=TRUE,0,IFERROR(I11,0))) | U11: =IF(A11="","",IF(P11=TRUE,0,IFERROR(J11,0))) | V11: =IF(A11="","",IF(P11=TRUE,0,IFERROR(K11,0))) | W11: =IF(A11="","",IF(P11=TRUE,0,IFERROR(L11,0))) | X11: =IF(A11="","",IF(P11=TRUE,0,IFERROR(H11,0)+IFERROR(I11,0)+IFERROR(L11,0))) | Y11: =IF(A11="",0,IF(G11=TRUE,IFERROR(H11,0)+IFERROR(I11,0)+IFERROR(J11,0)+IFERROR(K11,0)+IFERROR(L11,0),0)) | Z11: =IF(A11="",0,IF(AND(O11=TRUE,G11<>TRUE),IFERROR(H11,0)+IFERROR(I11,0)+IFERROR(J11,0)+IFERROR(K11,0)+IFERROR(L11,0),0))
M12: =IFERROR(IF(A12="","",IFERROR(VLOOKUP(A12,Raw_PriorMonth!A:E,5,FALSE),0)),0) | N12: =IF(A12="","",IFERROR(E12,0)+IFERROR(M12,0)) | O12: =IF(A12="","",IF(N12>=28,TRUE,FALSE)) | P12: =IF(A12="","",OR(G12=TRUE,O12=TRUE)) | Q12: =IF(A12="","",IFERROR(H12,0)+IFERROR(I12,0)+IFERROR(J12,0)+IFERROR(K12,0)+IFERROR(L12,0)) | R12: =IF(A12="","",IF(P12=TRUE,0,Q12)) | S12: =IF(A12="","",IF(P12=TRUE,0,IFERROR(H12,0))) | T12: =IF(A12="","",IF(P12=TRUE,0,IFERROR(I12,0))) | U12: =IF(A12="","",IF(P12=TRUE,0,IFERROR(J12,0))) | V12: =IF(A12="","",IF(P12=TRUE,0,IFERROR(K12,0))) | W12: =IF(A12="","",IF(P12=TRUE,0,IFERROR(L12,0))) | X12: =IF(A12="","",IF(P12=TRUE,0,IFERROR(H12,0)+IFERROR(I12,0)+IFERROR(L12,0))) | Y12: =IF(A12="",0,IF(G12=TRUE,IFERROR(H12,0)+IFERROR(I12,0)+IFERROR(J12,0)+IFERROR(K12,0)+IFERROR(L12,0),0)) | Z12: =IF(A12="",0,IF(AND(O12=TRUE,G12<>TRUE),IFERROR(H12,0)+IFERROR(I12,0)+IFERROR(J12,0)+IFERROR(K12,0)+IFERROR(L12,0),0))
M13: =IFERROR(IF(A13="","",IFERROR(VLOOKUP(A13,Raw_PriorMonth!A:E,5,FALSE),0)),0) | N13: =IF(A13="","",IFERROR(E13,0)+IFERROR(M13,0)) | O13: =IF(A13="","",IF(N13>=28,TRUE,FALSE)) | P13: =IF(A13="","",OR(G13=TRUE,O13=TRUE)) | Q13: =IF(A13="","",IFERROR(H13,0)+IFERROR(I13,0)+IFERROR(J13,0)+IFERROR(K13,0)+IFERROR(L13,0)) | R13: =IF(A13="","",IF(P13=TRUE,0,Q13)) | S13: =IF(A13="","",IF(P13=TRUE,0,IFERROR(H13,0))) | T13: =IF(A13="","",IF(P13=TRUE,0,IFERROR(I13,0))) | U13: =IF(A13="","",IF(P13=TRUE,0,IFERROR(J13,0))) | V13: =IF(A13="","",IF(P13=TRUE,0,IFERROR(K13,0))) | W13: =IF(A13="","",IF(P13=TRUE,0,IFERROR(L13,0))) | X13: =IF(A13="","",IF(P13=TRUE,0,IFERROR(H13,0)+IFERROR(I13,0)+IFERROR(L13,0))) | Y13: =IF(A13="",0,IF(G13=TRUE,IFERROR(H13,0)+IFERROR(I13,0)+IFERROR(J13,0)+IFERROR(K13,0)+IFERROR(L13,0),0)) | Z13: =IF(A13="",0,IF(AND(O13=TRUE,G13<>TRUE),IFERROR(H13,0)+IFERROR(I13,0)+IFERROR(J13,0)+IFERROR(K13,0)+IFERROR(L13,0),0))
... M501: =IFERROR(IF(A501="","",IFERROR(VLOOKUP(A501,Raw_PriorMonth!A:E,5,FALSE),0)),0) | N501: =IF(A501="","",IFERROR(E501,0)+IFERROR(M501,0)) | O501: =IF(A501="","",IF(N501>=28,TRUE,FALSE)) | P501: =IF(A501="","",OR(G501=TRUE,O501=TRUE)) | Q501: =IF(A501="","",IFERROR(H501,0)+IFERROR(I501,0)+IFERROR(J501,0)+IFERROR(K501,0)+IFERROR(L501,0)) | R501: =IF(A501="","",IF(P501=TRUE,0,Q501)) | S501: =IF(A501="","",IF(P501=TRUE,0,IFERROR(H501,0))) | T501: =IF(A501="","",IF(P501=TRUE,0,IFERROR(I501,0))) | U501: =IF(A501="","",IF(P501=TRUE,0,IFERROR(J501,0))) | V501: =IF(A501="","",IF(P501=TRUE,0,IFERROR(K501,0))) | W501: =IF(A501="","",IF(P501=TRUE,0,IFERROR(L501,0))) | X501: =IF(A501="","",IF(P501=TRUE,0,IFERROR(H501,0)+IFERROR(I501,0)+IFERROR(L501,0))) | Y501: =IF(A501="",0,IF(G501=TRUE,IFERROR(H501,0)+IFERROR(I501,0)+IFERROR(J501,0)+IFERROR(K501,0)+IFERROR(L501,0),0)) | Z501: =IF(A501="",0,IF(AND(O501=TRUE,G501<>TRUE),IFERROR(H501,0)+IFERROR(I501,0)+IFERROR(J501,0)+IFERROR(K501,0)+IFERROR(L501,0),0))

Sheet Raw_PriorMonth
A1: ReservationID | B1: GuestName | C1: CheckIn | D1: CheckOut | E1: NightsThisMonth | F1: ReservationSource | G1: StateExempt | H1: RoomRevenue | I1: PetFees | J1: OtherItemsAndServices | K1: Bartab | L1: RoomRateAdjustments | M1: IsNowExempt | N1: RefundableRevenue | O1: RefundableRoomRev | P1: RefundablePetFees | Q1: RefundableOther | R1: RefundableBartab | S1: RefundableRoomAdj | T1: RefundableLodging
M2: =IF(A2="","",IFERROR(VLOOKUP(A2,Raw_CurrentMonth!A:O,15,FALSE)=TRUE,FALSE)) | N2: =IF(A2="","",IF(M2=TRUE,IFERROR(H2,0)+IFERROR(I2,0)+IFERROR(J2,0)+IFERROR(K2,0)+IFERROR(L2,0),0)) | O2: =IF(A2="","",IF(M2=TRUE,IFERROR(H2,0),0)) | P2: =IF(A2="","",IF(M2=TRUE,IFERROR(I2,0),0)) | Q2: =IF(A2="","",IF(M2=TRUE,IFERROR(J2,0),0)) | R2: =IF(A2="","",IF(M2=TRUE,IFERROR(K2,0),0)) | S2: =IF(A2="","",IF(M2=TRUE,IFERROR(L2,0),0)) | T2: =IF(A2="","",IF(M2=TRUE,IFERROR(H2,0)+IFERROR(I2,0)+IFERROR(L2,0),0))
M3: =IF(A3="","",IFERROR(VLOOKUP(A3,Raw_CurrentMonth!A:O,15,FALSE)=TRUE,FALSE)) | N3: =IF(A3="","",IF(M3=TRUE,IFERROR(H3,0)+IFERROR(I3,0)+IFERROR(J3,0)+IFERROR(K3,0)+IFERROR(L3,0),0)) | O3: =IF(A3="","",IF(M3=TRUE,IFERROR(H3,0),0)) | P3: =IF(A3="","",IF(M3=TRUE,IFERROR(I3,0),0)) | Q3: =IF(A3="","",IF(M3=TRUE,IFERROR(J3,0),0)) | R3: =IF(A3="","",IF(M3=TRUE,IFERROR(K3,0),0)) | S3: =IF(A3="","",IF(M3=TRUE,IFERROR(L3,0),0)) | T3: =IF(A3="","",IF(M3=TRUE,IFERROR(H3,0)+IFERROR(I3,0)+IFERROR(L3,0),0))
M4: =IF(A4="","",IFERROR(VLOOKUP(A4,Raw_CurrentMonth!A:O,15,FALSE)=TRUE,FALSE)) | N4: =IF(A4="","",IF(M4=TRUE,IFERROR(H4,0)+IFERROR(I4,0)+IFERROR(J4,0)+IFERROR(K4,0)+IFERROR(L4,0),0)) | O4: =IF(A4="","",IF(M4=TRUE,IFERROR(H4,0),0)) | P4: =IF(A4="","",IF(M4=TRUE,IFERROR(I4,0),0)) | Q4: =IF(A4="","",IF(M4=TRUE,IFERROR(J4,0),0)) | R4: =IF(A4="","",IF(M4=TRUE,IFERROR(K4,0),0)) | S4: =IF(A4="","",IF(M4=TRUE,IFERROR(L4,0),0)) | T4: =IF(A4="","",IF(M4=TRUE,IFERROR(H4,0)+IFERROR(I4,0)+IFERROR(L4,0),0))
M5: =IF(A5="","",IFERROR(VLOOKUP(A5,Raw_CurrentMonth!A:O,15,FALSE)=TRUE,FALSE)) | N5: =IF(A5="","",IF(M5=TRUE,IFERROR(H5,0)+IFERROR(I5,0)+IFERROR(J5,0)+IFERROR(K5,0)+IFERROR(L5,0),0)) | O5: =IF(A5="","",IF(M5=TRUE,IFERROR(H5,0),0)) | P5: =IF(A5="","",IF(M5=TRUE,IFERROR(I5,0),0)) | Q5: =IF(A5="","",IF(M5=TRUE,IFERROR(J5,0),0)) | R5: =IF(A5="","",IF(M5=TRUE,IFERROR(K5,0),0)) | S5: =IF(A5="","",IF(M5=TRUE,IFERROR(L5,0),0)) | T5: =IF(A5="","",IF(M5=TRUE,IFERROR(H5,0)+IFERROR(I5,0)+IFERROR(L5,0),0))
M6: =IF(A6="","",IFERROR(VLOOKUP(A6,Raw_CurrentMonth!A:O,15,FALSE)=TRUE,FALSE)) | N6: =IF(A6="","",IF(M6=TRUE,IFERROR(H6,0)+IFERROR(I6,0)+IFERROR(J6,0)+IFERROR(K6,0)+IFERROR(L6,0),0)) | O6: =IF(A6="","",IF(M6=TRUE,IFERROR(H6,0),0)) | P6: =IF(A6="","",IF(M6=TRUE,IFERROR(I6,0),0)) | Q6: =IF(A6="","",IF(M6=TRUE,IFERROR(J6,0),0)) | R6: =IF(A6="","",IF(M6=TRUE,IFERROR(K6,0),0)) | S6: =IF(A6="","",IF(M6=TRUE,IFERROR(L6,0),0)) | T6: =IF(A6="","",IF(M6=TRUE,IFERROR(H6,0)+IFERROR(I6,0)+IFERROR(L6,0),0))
M7: =IF(A7="","",IFERROR(VLOOKUP(A7,Raw_CurrentMonth!A:O,15,FALSE)=TRUE,FALSE)) | N7: =IF(A7="","",IF(M7=TRUE,IFERROR(H7,0)+IFERROR(I7,0)+IFERROR(J7,0)+IFERROR(K7,0)+IFERROR(L7,0),0)) | O7: =IF(A7="","",IF(M7=TRUE,IFERROR(H7,0),0)) | P7: =IF(A7="","",IF(M7=TRUE,IFERROR(I7,0),0)) | Q7: =IF(A7="","",IF(M7=TRUE,IFERROR(J7,0),0)) | R7: =IF(A7="","",IF(M7=TRUE,IFERROR(K7,0),0)) | S7: =IF(A7="","",IF(M7=TRUE,IFERROR(L7,0),0)) | T7: =IF(A7="","",IF(M7=TRUE,IFERROR(H7,0)+IFERROR(I7,0)+IFERROR(L7,0),0))
M8: =IF(A8="","",IFERROR(VLOOKUP(A8,Raw_CurrentMonth!A:O,15,FALSE)=TRUE,FALSE)) | N8: =IF(A8="","",IF(M8=TRUE,IFERROR(H8,0)+IFERROR(I8,0)+IFERROR(J8,0)+IFERROR(K8,0)+IFERROR(L8,0),0)) | O8: =IF(A8="","",IF(M8=TRUE,IFERROR(H8,0),0)) | P8: =IF(A8="","",IF(M8=TRUE,IFERROR(I8,0),0)) | Q8: =IF(A8="","",IF(M8=TRUE,IFERROR(J8,0),0)) | R8: =IF(A8="","",IF(M8=TRUE,IFERROR(K8,0),0)) | S8: =IF(A8="","",IF(M8=TRUE,IFERROR(L8,0),0)) | T8: =IF(A8="","",IF(M8=TRUE,IFERROR(H8,0)+IFERROR(I8,0)+IFERROR(L8,0),0))
M9: =IF(A9="","",IFERROR(VLOOKUP(A9,Raw_CurrentMonth!A:O,15,FALSE)=TRUE,FALSE)) | N9: =IF(A9="","",IF(M9=TRUE,IFERROR(H9,0)+IFERROR(I9,0)+IFERROR(J9,0)+IFERROR(K9,0)+IFERROR(L9,0),0)) | O9: =IF(A9="","",IF(M9=TRUE,IFERROR(H9,0),0)) | P9: =IF(A9="","",IF(M9=TRUE,IFERROR(I9,0),0)) | Q9: =IF(A9="","",IF(M9=TRUE,IFERROR(J9,0),0)) | R9: =IF(A9="","",IF(M9=TRUE,IFERROR(K9,0),0)) | S9: =IF(A9="","",IF(M9=TRUE,IFERROR(L9,0),0)) | T9: =IF(A9="","",IF(M9=TRUE,IFERROR(H9,0)+IFERROR(I9,0)+IFERROR(L9,0),0))
M10: =IF(A10="","",IFERROR(VLOOKUP(A10,Raw_CurrentMonth!A:O,15,FALSE)=TRUE,FALSE)) | N10: =IF(A10="","",IF(M10=TRUE,IFERROR(H10,0)+IFERROR(I10,0)+IFERROR(J10,0)+IFERROR(K10,0)+IFERROR(L10,0),0)) | O10: =IF(A10="","",IF(M10=TRUE,IFERROR(H10,0),0)) | P10: =IF(A10="","",IF(M10=TRUE,IFERROR(I10,0),0)) | Q10: =IF(A10="","",IF(M10=TRUE,IFERROR(J10,0),0)) | R10: =IF(A10="","",IF(M10=TRUE,IFERROR(K10,0),0)) | S10: =IF(A10="","",IF(M10=TRUE,IFERROR(L10,0),0)) | T10: =IF(A10="","",IF(M10=TRUE,IFERROR(H10,0)+IFERROR(I10,0)+IFERROR(L10,0),0))
M11: =IF(A11="","",IFERROR(VLOOKUP(A11,Raw_CurrentMonth!A:O,15,FALSE)=TRUE,FALSE)) | N11: =IF(A11="","",IF(M11=TRUE,IFERROR(H11,0)+IFERROR(I11,0)+IFERROR(J11,0)+IFERROR(K11,0)+IFERROR(L11,0),0)) | O11: =IF(A11="","",IF(M11=TRUE,IFERROR(H11,0),0)) | P11: =IF(A11="","",IF(M11=TRUE,IFERROR(I11,0),0)) | Q11: =IF(A11="","",IF(M11=TRUE,IFERROR(J11,0),0)) | R11: =IF(A11="","",IF(M11=TRUE,IFERROR(K11,0),0)) | S11: =IF(A11="","",IF(M11=TRUE,IFERROR(L11,0),0)) | T11: =IF(A11="","",IF(M11=TRUE,IFERROR(H11,0)+IFERROR(I11,0)+IFERROR(L11,0),0))
M12: =IF(A12="","",IFERROR(VLOOKUP(A12,Raw_CurrentMonth!A:O,15,FALSE)=TRUE,FALSE)) | N12: =IF(A12="","",IF(M12=TRUE,IFERROR(H12,0)+IFERROR(I12,0)+IFERROR(J12,0)+IFERROR(K12,0)+IFERROR(L12,0),0)) | O12: =IF(A12="","",IF(M12=TRUE,IFERROR(H12,0),0)) | P12: =IF(A12="","",IF(M12=TRUE,IFERROR(I12,0),0)) | Q12: =IF(A12="","",IF(M12=TRUE,IFERROR(J12,0),0)) | R12: =IF(A12="","",IF(M12=TRUE,IFERROR(K12,0),0)) | S12: =IF(A12="","",IF(M12=TRUE,IFERROR(L12,0),0)) | T12: =IF(A12="","",IF(M12=TRUE,IFERROR(H12,0)+IFERROR(I12,0)+IFERROR(L12,0),0))
M13: =IF(A13="","",IFERROR(VLOOKUP(A13,Raw_CurrentMonth!A:O,15,FALSE)=TRUE,FALSE)) | N13: =IF(A13="","",IF(M13=TRUE,IFERROR(H13,0)+IFERROR(I13,0)+IFERROR(J13,0)+IFERROR(K13,0)+IFERROR(L13,0),0)) | O13: =IF(A13="","",IF(M13=TRUE,IFERROR(H13,0),0)) | P13: =IF(A13="","",IF(M13=TRUE,IFERROR(I13,0),0)) | Q13: =IF(A13="","",IF(M13=TRUE,IFERROR(J13,0),0)) | R13: =IF(A13="","",IF(M13=TRUE,IFERROR(K13,0),0)) | S13: =IF(A13="","",IF(M13=TRUE,IFERROR(L13,0),0)) | T13: =IF(A13="","",IF(M13=TRUE,IFERROR(H13,0)+IFERROR(I13,0)+IFERROR(L13,0),0))
... M501: =IF(A501="","",IFERROR(VLOOKUP(A501,Raw_CurrentMonth!A:O,15,FALSE)=TRUE,FALSE)) | N501: =IF(A501="","",IF(M501=TRUE,IFERROR(H501,0)+IFERROR(I501,0)+IFERROR(J501,0)+IFERROR(K501,0)+IFERROR(L501,0),0)) | O501: =IF(A501="","",IF(M501=TRUE,IFERROR(H501,0),0)) | P501: =IF(A501="","",IF(M501=TRUE,IFERROR(I501,0),0)) | Q501: =IF(A501="","",IF(M501=TRUE,IFERROR(J501,0),0)) | R501: =IF(A501="","",IF(M501=TRUE,IFERROR(K501,0),0)) | S501: =IF(A501="","",IF(M501=TRUE,IFERROR(L501,0),0)) | T501: =IF(A501="","",IF(M501=TRUE,IFERROR(H501,0)+IFERROR(I501,0)+IFERROR(L501,0),0))

Sheet Tax_Summary
A1: Tax Summary — Auto-Calculated
A2: Filing month: | B2: =Setup!B4
A3: Category | B3: Line Amount | C3: Total Amount | E3: Tax Component | F3: Taxable Base | G3: Tax | H3: Use Tax | I3: Notes
A4: Total Rooms Revenue (taxable) | B4: =SUM(Raw_CurrentMonth!S2:S501) | C4: =B4 | E4: State Sales Tax | F4: =C9 | G4: =F4*Setup!B9 | H4: =Setup!B6*Setup!B9 | I4: Base: all taxable revenue. Use tax applied to Setup!B6.
A5: Pet Fees (taxable) | B5: =SUM(Raw_CurrentMonth!T2:T501) | C5: =B5 | E5: Municipal Gross Receipts (BBB) — Tea | F5: =C9+Setup!B6 | G5: =F5*Setup!B11 | I5: 1% on lodging/prepared food/alcohol/admissions + use tax base.
A6: All Other Items and Services (taxable) | B6: =SUM(Raw_CurrentMonth!U2:U501) | C6: =B6 | E6: Municipal Sales Tax (Tea) | F6: =C9+Setup!B6 | G6: =F6*Setup!B10 | I6: 2% on all sales + use tax base (Tea municipal rate).
A7: Bartab (taxable) | B7: =SUM(Raw_CurrentMonth!V2:V501) | C7: =B7 | E7: Tourism Tax (lodging only) | F7: =SUM(Raw_CurrentMonth!X2:X501) | G7: =F7*Setup!B12 | I7: 1.5% on lodging gross receipts (rooms + pet fees + room adjustments).
A8: Room Rate Adjustments (taxable) | B8: =SUM(Raw_CurrentMonth!W2:W501) | C8: =B8 | E8: Prior-Month Tax Refund (28-day) | F8: =C17 | G8: =-(F8*(Setup!B9+Setup!B10+Setup!B11)) | I8: Tax paid last month on reservations that are now 28-day-exempt. Lodging portion also gets tourism tax refund (row 9).
A9: Total Taxable Sales Base | C9: =SUM(C4:C8) | E9: Prior-Month Tourism Refund (28-day) | F9: =SUM(Raw_PriorMonth!T2:T501) | G9: =-(F9*Setup!B12) | I9: 1.5% refund on prior-month lodging revenue now 28-day-exempt.
A11: Prior Month 28-Day Refund (revenue backed out) | E11: TOTAL SALES TAX (net of refunds) | G11: =SUM(G4:G9)
A12: Rooms revenue refund | C12: =SUM(Raw_PriorMonth!O2:O501) | E12: TOTAL USE TAX (state) | H12: =H4
A13: Pet fees refund | C13: =SUM(Raw_PriorMonth!P2:P501) | E13: GRAND TOTAL DUE | G13: =G11+H12
A14: Other items refund | C14: =SUM(Raw_PriorMonth!Q2:Q501)
A15: Bartab refund | C15: =SUM(Raw_PriorMonth!R2:R501)
A16: Room adjustments refund | C16: =SUM(Raw_PriorMonth!S2:S501)
A17: Total Prior-Month Refund Base | C17: =SUM(C12:C16)
A19: Exempt Revenue Summary (informational — report to state as exempt)
A20: State-agency exempt revenue (current month) | C20: =SUM(Raw_CurrentMonth!Y2:Y501)
A21: 28-day exempt revenue (current month) | C21: =SUM(Raw_CurrentMonth!Z2:Z501)

Sheet State_Filing
A1: State Filing — Enter These Numbers on the SD DOR Portal
A2: Filing month: | B2: =Setup!B4
A4: Line | B4: Description | C4: Taxable Base | D4: Tax Due
A5: 1 | B5: Gross sales (rooms + pet + other + bar + adj — current month, taxable + exempt) | C5: =Tax_Summary!C9+Tax_Summary!C20+Tax_Summary!C21
A6: 2 | B6: Exempt sales (state-agency + 28-day) | C6: =Tax_Summary!C20+Tax_Summary!C21
A7: 3 | B7: Net taxable sales (line 1 − line 2) | C7: =C5-C6
A8: 4 | B8: State sales tax (4.2%) | C8: =Tax_Summary!F4 | D8: =Tax_Summary!G4
A9: 5 | B9: Municipal sales tax — Tea (2.0%) | C9: =Tax_Summary!F6 | D9: =Tax_Summary!G6
A10: 6 | B10: Municipal Gross Receipts (BBB) — Tea (1.0%) | C10: =Tax_Summary!F5 | D10: =Tax_Summary!G5
A11: 7 | B11: Tourism tax (1.5%, lodging only) | C11: =Tax_Summary!F7 | D11: =Tax_Summary!G7
A12: 8 | B12: Use tax (state, 4.2% on use tax base) | C12: =Setup!B6 | D12: =Tax_Summary!H4
A13: 9 | B13: Prior-month 28-day sales tax refund (credit) | C13: =Tax_Summary!F8 | D13: =Tax_Summary!G8
A14: 10 | B14: Prior-month 28-day tourism refund (credit) | C14: =Tax_Summary!F9 | D14: =Tax_Summary!G9
A15: 11 | B15: GRAND TOTAL DUE | D15: =Tax_Summary!G13
A17: Red numbers are what staff types into the SD DOR portal. Double-check line-by-line against the portal screens. DO NOT auto-submit — tax filing has legal liability; a human must review and click submit.
